frappymongouser/__init__.py
frappymongouser/user_store.py
frappymongouser/user_token_store.py
frappymongouser-1.5.1.dist-info/LICENSE
frappymongouser-1.5.1.dist-info/METADATA
frappymongouser-1.5.1.dist-info/WHEEL
frappymongouser-1.5.1.dist-info/top_level.txt
frappymongouser-1.5.1.dist-info/RECORD
