Metadata-Version: 2.1
Name: frappymongouser
Version: 1.5.1
Summary: Store Implementation for Users in MongoDB
Home-page: https://github.com/ilfrich/frappy-py-mongo-user-store
Author: Peter Ilfrich
Author-email: das-peter@gmx.de
License: UNKNOWN
Platform: UNKNOWN
Requires-Dist: pbu (>=1.0.0)
Requires-Dist: pbumongo (>=1.0.0)
